comparator_stage.vhd
--
-- AAD 2025/2026, single-bit comparator stage
--
-- Implements one stage of a bit-by-bit comparator chain
-- Compares one bit position and propagates comparison results
--

library IEEE;
use IEEE.std_logic_1164.all;

entity comparator_stage is
  port
  (
    a_bit   : in  std_logic;  -- bit from operand a
    b_bit   : in  std_logic;  -- bit from operand b
    old_lt  : in  std_logic;  -- previous less-than result
    old_eq  : in  std_logic;  -- previous equal result
    old_gt  : in  std_logic;  -- previous greater-than result
    new_lt  : out std_logic;  -- updated less-than result
    new_eq  : out std_logic;  -- updated equal result
    new_gt  : out std_logic   -- updated greater-than result
  );
end comparator_stage;

architecture behavioral of comparator_stage is
  signal s_lt : std_logic;
  signal s_eq : std_logic;
  signal s_gt : std_logic;
begin
  process(a_bit, b_bit, old_lt, old_eq, old_gt)
  begin
    if a_bit = b_bit then
      -- Bits are equal, keep previous results
      s_lt <= old_lt;
      s_eq <= old_eq;
      s_gt <= old_gt;
    elsif a_bit = '1' then
      -- a_bit=1 and b_bit=0, so a > b at this position
      s_lt <= '0';
      s_eq <= '0';
      s_gt <= '1';
    else
      -- a_bit=0 and b_bit=1, so a < b at this position
      s_lt <= '1';
      s_eq <= '0';
      s_gt <= '0';
    end if;
  end process;
  
  -- 5 ps delay per stage as specified
  new_lt <= transport s_lt after 5 ps;
  new_eq <= transport s_eq after 5 ps;
  new_gt <= transport s_gt after 5 ps;
  
end behavioral;

comparator_n.vhd
--
-- AAD 2025/2026, n-bit comparator
--
-- for extra credit, implement this also using chains of unsigned comparators:
--
-- unsigned comparator stage (one per bit)
--   in   a_bit   b_bit   old_lt   old_eq   old_gt
--   out                  new_lt   new_eq   new_gt
-- logic, start from the least significant bit with old_lt=old_gt=0 and old_eq=1
--   if a_bit=b_bit (no change, keep the earlier result)
--     new_lt=old_lt   new_eq=old_eq   new_gt=old_gt
--   else if a_bit=1 (a is greater because a_bit=1 and b_bit=0)
--     new_lt=0        new_eq=0        new_gt=1
--   else  (a is smaller because a_bit=0 and b_bit=1)
--     new_lt=1        new_eq=0        new_gt=0
-- use a transport delay of 5 ps per stage
--

library IEEE;
use IEEE.std_logic_1164.all;
use IEEE.numeric_std.all;

entity comparator_n is
  generic
  (
    N : positive
  );
  port
  (
    a  : in  std_logic_vector(N-1 downto 0);
    b  : in  std_logic_vector(N-1 downto 0);
    lt : out std_logic; -- '1' if a<b, '0' otherwise
    eq : out std_logic; -- '1' if a=b, '0' otherwise
    gt : out std_logic  -- '1' if a>b, '0' otherwise
  );
end comparator_n;

architecture structural of comparator_n is
  -- Component declaration for single-bit comparator stage
  component comparator_stage is
    port
    (
      a_bit   : in  std_logic;
      b_bit   : in  std_logic;
      old_lt  : in  std_logic;
      old_eq  : in  std_logic;
      old_gt  : in  std_logic;
      new_lt  : out std_logic;
      new_eq  : out std_logic;
      new_gt  : out std_logic
    );
  end component;
  
  -- Internal signals for chaining comparator stages
  -- Array of N+1 elements: index 0 is initial, indices 1..N are outputs of each stage
  type cmp_chain_t is array(0 to N) of std_logic;
  signal chain_lt : cmp_chain_t;
  signal chain_eq : cmp_chain_t;
  signal chain_gt : cmp_chain_t;
  
begin
  
  -- Initialize the comparison chain (start from LSB with lt=0, eq=1, gt=0)
  chain_lt(0) <= '0';
  chain_eq(0) <= '1';
  chain_gt(0) <= '0';
  
  -- Generate N comparator stages, one per bit
  -- Start from LSB (bit 0) and propagate to MSB (bit N-1)
  gen_stages : for i in 0 to N-1 generate
    stage : comparator_stage
      port map
      (
        a_bit   => a(i),
        b_bit   => b(i),
        old_lt  => chain_lt(i),
        old_eq  => chain_eq(i),
        old_gt  => chain_gt(i),
        new_lt  => chain_lt(i+1),
        new_eq  => chain_eq(i+1),
        new_gt  => chain_gt(i+1)
      );
  end generate gen_stages;
  
  -- Output the final results from the last stage
  lt <= chain_lt(N);
  eq <= chain_eq(N);
  gt <= chain_gt(N);
  
end structural;

comparator_n_tb.vhd
--
-- AAD 2025/2026, comparator testbench
--

library IEEE;
use IEEE.std_logic_1164.all;
use IEEE.numeric_std.all;

entity comparator_n_tb is
end comparator_n_tb;

architecture stimulus of comparator_n_tb is
  -- constants
  constant N : positive := 4;
  -- the interface signals
  signal s_a  : std_logic_vector(N-1 downto 0);
  signal s_b  : std_logic_vector(N-1 downto 0);
  signal s_lt : std_logic;
  signal s_eq : std_logic;
  signal s_gt : std_logic;
begin
  uut : entity work.comparator_n(structural)
               generic map
               (
                 N => N
               )
               port map
               (
                 a  => s_a,
                 b  => s_b,
                 lt => s_lt,
                 eq => s_eq,
                 gt => s_gt
               );
  stim : process is
  begin
    s_a <= "0010";
    s_b <= "0010";
    wait for 200 ps;
    s_a <= "1011";
    s_b <= "0100";
    wait for 200 ps;
    s_a <= "0101";
    s_b <= "1010";
    wait for 200 ps;
    s_a <= "0111";
    s_b <= "0111";
    wait for 200 ps;
    s_a <= "1111";
    s_b <= "1110";
    wait for 200 ps;
    wait;
  end process;
end stimulus;

comparator_n.vcd
$date
  Fri Jan  9 23:42:47 2026
$end
$version
  GHDL v0
$end
$timescale
  1 fs
$end
$scope module standard $end
$upscope $end
$scope module textio $end
$upscope $end
$scope module std_logic_1164 $end
$upscope $end
$scope module numeric_std $end
$upscope $end
$scope module comparator_n_tb $end
$var reg 4 ! s_a[3:0] $end
$var reg 4 " s_b[3:0] $end
$var reg 1 # s_lt $end
$var reg 1 $ s_eq $end
$var reg 1 % s_gt $end
$scope module uut $end
$var reg 4 & a[3:0] $end
$var reg 4 ' b[3:0] $end
$var reg 1 ( lt $end
$var reg 1 ) eq $end
$var reg 1 * gt $end
$var reg 5 + chain_lt[0:4] $end
$var reg 5 , chain_eq[0:4] $end
$var reg 5 - chain_gt[0:4] $end
$scope module gen_stages(0) $end
$scope module stage $end
$var reg 1 . a_bit $end
$var reg 1 / b_bit $end
$var reg 1 0 old_lt $end
$var reg 1 1 old_eq $end
$var reg 1 2 old_gt $end
$var reg 1 3 new_lt $end
$var reg 1 4 new_eq $end
$var reg 1 5 new_gt $end
$var reg 1 6 s_lt $end
$var reg 1 7 s_eq $end
$var reg 1 8 s_gt $end
$upscope $end
$upscope $end
$scope module gen_stages(1) $end
$scope module stage $end
$var reg 1 9 a_bit $end
$var reg 1 : b_bit $end
$var reg 1 ; old_lt $end
$var reg 1 < old_eq $end
$var reg 1 = old_gt $end
$var reg 1 > new_lt $end
$var reg 1 ? new_eq $end
$var reg 1 @ new_gt $end
$var reg 1 A s_lt $end
$var reg 1 B s_eq $end
$var reg 1 C s_gt $end
$upscope $end
$upscope $end
$scope module gen_stages(2) $end
$scope module stage $end
$var reg 1 D a_bit $end
$var reg 1 E b_bit $end
$var reg 1 F old_lt $end
$var reg 1 G old_eq $end
$var reg 1 H old_gt $end
$var reg 1 I new_lt $end
$var reg 1 J new_eq $end
$var reg 1 K new_gt $end
$var reg 1 L s_lt $end
$var reg 1 M s_eq $end
$var reg 1 N s_gt $end
$upscope $end
$upscope $end
$scope module gen_stages(3) $end
$scope module stage $end
$var reg 1 O a_bit $end
$var reg 1 P b_bit $end
$var reg 1 Q old_lt $end
$var reg 1 R old_eq $end
$var reg 1 S old_gt $end
$var reg 1 T new_lt $end
$var reg 1 U new_eq $end
$var reg 1 V new_gt $end
$var reg 1 W s_lt $end
$var reg 1 X s_eq $end
$var reg 1 Y s_gt $end
$upscope $end
$upscope $end
$upscope $end
$upscope $end
$enddefinitions $end
#0
b0010 !
b0010 "
U#
U$
U%
b0010 &
b0010 '
U(
U)
U*
b0UUUU +
b1UUUU ,
b0UUUU -
0.
0/
00
11
02
U3
U4
U5
06
17
08
19
1:
U;
U<
U=
U>
U?
U@
UA
UB
UC
0D
0E
UF
UG
UH
UI
UJ
UK
UL
UM
UN
0O
0P
UQ
UR
US
UT
UU
UV
UW
UX
UY
#5000
b00UUU +
b11UUU ,
b00UUU -
03
14
05
0;
1<
0=
U>
U?
U@
0A
1B
0C
UI
UJ
UK
UT
UU
UV
#10000
b000UU +
b111UU ,
b000UU -
0>
1?
0@
0F
1G
0H
0L
1M
0N
#15000
b0000U +
b1111U ,
b0000U -
0I
1J
0K
0Q
1R
0S
0W
1X
0Y
#20000
0#
1$
0%
0(
1)
0*
b00000 +
b11111 ,
b00000 -
0T
1U
0V
#200000
b1011 !
b0100 "
b1011 &
b0100 '
1.
07
18
0:
0B
1C
1E
1L
0M
1O
0X
1Y
#205000
0$
1%
0)
1*
b00010 +
b10000 ,
b01101 -
04
15
0<
1=
0?
1@
0G
1H
1I
0J
1Q
0R
0U
1V
#400000
b0101 !
b1010 "
b0101 &
b1010 '
09
1:
1A
0C
1D
0E
0L
1N
0O
1P
1W
0Y
#405000
1#
0%
1(
0*
b00101 +
b01010 -
1>
0@
1F
0H
0I
1K
0Q
1S
1T
0V
#600000
b0111 !
b0111 "
b0111 &
b0111 '
1/
17
08
19
0A
1C
1E
1L
0N
0P
0W
1Y
#605000
0#
1%
0(
1*
b00010 +
b11000 ,
b00101 -
14
05
1<
0=
0>
1@
1B
0C
0F
1H
1I
0K
0L
1N
1Q
0S
0T
1V
1W
0Y
#610000
1#
0%
1(
0*
b00001 +
b11100 ,
b00010 -
1?
0@
1G
0H
0I
1K
1M
0N
0Q
1S
1T
0V
0W
1Y
#615000
0#
1%
0(
1*
b00000 +
b11110 ,
b00001 -
1J
0K
1R
0S
0T
1V
1X
0Y
#620000
1$
0%
1)
0*
b11111 ,
b00000 -
1U
0V
#800000
b1111 !
b1110 "
b1111 &
b1110 '
0/
07
18
1O
1P
#805000
b10111 ,
b01000 -
04
15
0<
1=
0B
1C
#810000
b10011 ,
b01100 -
0?
1@
0G
1H
0M
1N
#815000
b10001 ,
b01110 -
0J
1K
0R
1S
0X
1Y
#820000
0$
1%
0)
1*
b10000 ,
b01111 -
0U
1V
